large_file_splitter/__init__.py
large_file_splitter/test.py
large_file_splitter-0.2.0.dist-info/METADATA
large_file_splitter-0.2.0.dist-info/WHEEL
large_file_splitter-0.2.0.dist-info/top_level.txt
large_file_splitter-0.2.0.dist-info/RECORD
