Metadata-Version: 2.1
Name: large-file-splitter
Version: 0.2.0
Summary: The tool considers a file so large that it does not fit in memory as a single string and performs a split process of the string. The tool stores the result as separate files.
Home-page: https://github.co.jp/
Author: bib_inf
Author-email: contact.bibinf@gmail.com
License: CC0 v1.0
Platform: UNKNOWN
Classifier: Programming Language :: Python :: 3
Classifier: License :: CC0 1.0 Universal (CC0 1.0) Public Domain Dedication
Requires-Dist: ezpip
Requires-Dist: sout (>=1.2.1)
Requires-Dist: relpath
